py_near_primitives-0.2.12.dist-info/METADATA
py_near_primitives-0.2.12.dist-info/WHEEL
py_near_primitives-0.2.12.dist-info/licenses/LICENSE
py_near_primitives/__init__.py
py_near_primitives/py_near_primitives.abi3.so
py_near_primitives-0.2.12.dist-info/RECORD
