Metadata-Version: 2.4
Name: py_near_primitives
Version: 0.2.12
Classifier: Programming Language :: Rust
Classifier: Programming Language :: Python :: Implementation :: CPython
Classifier: Programming Language :: Python :: Implementation :: PyPy
License-File: LICENSE
Summary: Python bindings for NEAR Rust primitives.
Author-email: pvolnov <peter@hot-labs.org>
Requires-Python: >=3.7
Project-URL: homepage, https://github.com/pvolnov/near-primitives
Project-URL: documentation, https://github.com/pvolnov/near-primitives
Project-URL: repository, https://github.com/pvolnov/near-primitives
